{"timestamp": "2026-06-10T14:03:29Z", "quotes": {"NVDA": {"symbol": "NVDA", "price": 205.63, "prevClose": 208.19, "change": -2.56, "changePercent": -1.23, "volume": 27804472}, "AMD": {"symbol": "AMD", "price": 467.99, "prevClose": 475.51, "change": -7.52, "changePercent": -1.58, "volume": 4764375}, "AVGO": {"symbol": "AVGO", "price": 375.46, "prevClose": 392.16, "change": -16.7, "changePercent": -4.26, "volume": 8122555}, "TSM": {"symbol": "TSM", "price": 418.3, "prevClose": 427.92, "change": -9.62, "changePercent": -2.25, "volume": 2692893}, "MSFT": {"symbol": "MSFT", "price": 404.37, "prevClose": 403.41, "change": 0.96, "changePercent": 0.24, "volume": 5474655}, "AMZN": {"symbol": "AMZN", "price": 241.44, "prevClose": 244.19, "change": -2.75, "changePercent": -1.13, "volume": 5536318}, "GOOGL": {"symbol": "GOOGL", "price": 366.38, "prevClose": 364.26, "change": 2.12, "changePercent": 0.58, "volume": 5585491}, "ORCL": {"symbol": "ORCL", "price": 208.81, "prevClose": 205.81, "change": 3.0, "changePercent": 1.46, "volume": 5830236}, "CRM": {"symbol": "CRM", "price": 175.02, "prevClose": 175.35, "change": -0.33, "changePercent": -0.19, "volume": 1908919}, "PLTR": {"symbol": "PLTR", "price": 132.3, "prevClose": 132.07, "change": 0.23, "changePercent": 0.17, "volume": 5865655}, "SNOW": {"symbol": "SNOW", "price": 246.86, "prevClose": 239.66, "change": 7.2, "changePercent": 3.0, "volume": 1143451}, "CRWD": {"symbol": "CRWD", "price": 657.72, "prevClose": 644.93, "change": 12.79, "changePercent": 1.98, "volume": 365134}, "PANW": {"symbol": "PANW", "price": 264.24, "prevClose": 260.52, "change": 3.72, "changePercent": 1.43, "volume": 1089675}, "ZS": {"symbol": "ZS", "price": 128.05, "prevClose": 125.84, "change": 2.21, "changePercent": 1.76, "volume": 600447}, "NET": {"symbol": "NET", "price": 229.19, "prevClose": 236.13, "change": -6.94, "changePercent": -2.94, "volume": 857680}, "S": {"symbol": "S", "price": 15.26, "prevClose": 15.24, "change": 0.02, "changePercent": 0.13, "volume": 991017}}}